flask_pre_configured_loggers.py
flask_pre_configured_loggers-0.1.1.dist-info/RECORD
flask_pre_configured_loggers-0.1.1.dist-info/DESCRIPTION.rst
flask_pre_configured_loggers-0.1.1.dist-info/top_level.txt
flask_pre_configured_loggers-0.1.1.dist-info/METADATA
flask_pre_configured_loggers-0.1.1.dist-info/WHEEL
flask_pre_configured_loggers-0.1.1.dist-info/metadata.json
